{
  "title": "Front Door Access Logs Enabled",
  "category": "Front Door",
  "description": "Ensures that Azure Front Door Access Log is enabled.",
  "more_info": "Azure Front Door captures several types of logs. Access logs can be used to identify slow requests, determine error rates, and understand how Front Door's caching behavior is working for your solution.",
  "link": "https://learn.microsoft.com/en-us/azure/frontdoor/standard-premium/how-to-logs",
  "recommended_action": "Ensure that diagnostic setting for Front Door Access Log is enabled."
}

